pycallflow/__about__.py
pycallflow/__init__.py
pycallflow/__main__.py
pycallflow/analyzeCallFlow.py
pycallflow/buildDeclaredEntitiesDB.py
pycallflow/buildFileDB.py
pycallflow/callFlowData.py
pycallflow/callflow.py
pycallflow/cflow_importlib.py
pycallflow/finalResults.py
pycallflow/output.py
pycallflow-0.2.0.dist-info/METADATA
pycallflow-0.2.0.dist-info/WHEEL
pycallflow-0.2.0.dist-info/licenses/LICENSE.txt
pycallflow-0.2.0.dist-info/RECORD
