Metadata-Version: 2.1
Name: pycallflow
Version: 0.2.0
Summary: Maps function, class, and method calls in python projects, modules, and files
Project-URL: Documentation, https://github.com/richmr/pycallflow#readme
Project-URL: Issues, https://github.com/richmr/pycallflow/issues
Project-URL: Source, https://github.com/richmr/pycallflow
Author-email: Michael Rich <richmr2174@gmail.com>
License-Expression: MIT
License-File: LICENSE.txt
Classifier: Development Status :: 4 - Beta
Classifier: Programming Language :: Python
Classifier: Programming Language :: Python :: 3.7
Classifier: Programming Language :: Python :: 3.8
Classifier: Programming Language :: Python :: 3.9
Classifier: Programming Language :: Python :: 3.10
Classifier: Programming Language :: Python :: 3.11
Classifier: Programming Language :: Python :: Implementation :: CPython
Classifier: Programming Language :: Python :: Implementation :: PyPy
Requires-Python: >=3.7
Requires-Dist: networkx
Requires-Dist: pydot
Requires-Dist: tabulate
